ELEP/elep/ensemble_coherence.py
ELEP/elep/ensemble_learners.py
ELEP/elep/ensemble_statistics.py
ELEP/elep/mbf.py
ELEP/elep/mbf_utils.py
ELEP/elep/trigger_func.py
ELEP/src/ensemble_coherence.py
ELEP/src/ensemble_learners.py
ELEP/src/ensemble_statistics.py
ELEP/src/mbf.py
ELEP/src/mbf_utils.py
ELEP/src/trigger_func.py
ELEP/utils/plot_utils.py
ELEP-0.0.2.dist-info/LICENSE
ELEP-0.0.2.dist-info/METADATA
ELEP-0.0.2.dist-info/WHEEL
ELEP-0.0.2.dist-info/top_level.txt
ELEP-0.0.2.dist-info/RECORD
