Metadata-Version: 2.1
Name: ELEP
Version: 0.0.2
Summary: Ensemble Learning for Earthquake Processing
Author-email: Congcong Yuan <cyuan@g.harvard.edu>
Maintainer-email: Congcong Yuan <cyuan@g.harvard.edu>, Yiyu Ni <niyiyu@uw.edu>
License: GPLv3
Project-URL: GitHub, https://github.com/congcy/ELEP
Project-URL: Documentation, https://ssec-python-project-template.readthedocs.io/en/latest
Project-URL: Issues, https://github.com/othneildrew/Best-README-Template/issues
Keywords: seismology,machine learning,ensemble learning,seismic signal processing
Classifier: Intended Audience :: Science/Research
Classifier: Topic :: Scientific/Engineering
Classifier: Programming Language :: Python :: 3.8
Classifier: Operating System :: OS Independent
Classifier: License :: OSI Approved :: GNU General Public License v3 (GPLv3)
Requires-Python: >=3.8
License-File: LICENSE
Requires-Dist: numpy (>=1.21.6)
Requires-Dist: pandas (>=1.1)
Requires-Dist: h5py (>=3.1)
Requires-Dist: obspy (>=1.2)
Requires-Dist: tqdm (>=4.52)
Requires-Dist: torch (>=1.10.0)
Requires-Dist: scipy (>=1.5)
Requires-Dist: nest-asyncio (>=1.5.3)
Provides-Extra: development
Requires-Dist: flake8 ; extra == 'development'
Requires-Dist: black ; extra == 'development'
Requires-Dist: isort ; extra == 'development'
Requires-Dist: pre-commit ; extra == 'development'
Provides-Extra: tests
Requires-Dist: pytest ; extra == 'tests'
Requires-Dist: pytest-asyncio ; extra == 'tests'
